dcm_classifier/README.md
dcm_classifier/__init__.py
dcm_classifier/classify_support.py
dcm_classifier/dicom_config.py
dcm_classifier/dicom_series.py
dcm_classifier/dicom_validator.py
dcm_classifier/dicom_volume.py
dcm_classifier/example_image_processing.py
dcm_classifier/image_type_inference.py
dcm_classifier/study_processing.py
dcm_classifier/test.py
dcm_classifier/utility_functions.py
dcm_classifier/models/ova_rf_classifier.onnx
dcm_classifier-0.9.9.dist-info/METADATA
dcm_classifier-0.9.9.dist-info/WHEEL
dcm_classifier-0.9.9.dist-info/licenses/LICENSE
dcm_classifier-0.9.9.dist-info/RECORD
