Metadata-Version: 2.4
Name: dcm_classifier
Version: 0.9.9
Summary: This is a consolidation of work from NAMIC efforts primarily at the University of Iowa.
Author-email: Michal Brzus <michal-brzus@uiowa.edu>, Hans Johnson <hans-johnson@uiowa.edu>, Cavan Riley <cavan-riley@uiowa.edu>
License-File: LICENSE
Classifier: Operating System :: OS Independent
Classifier: Programming Language :: Python :: 3
Requires-Python: >=3.10
Requires-Dist: deprecation>=2.1.0
Requires-Dist: itk-core>=5.3.0
Requires-Dist: itk-filtering>=5.3.0
Requires-Dist: itk-io>=5.3.0
Requires-Dist: itk-numerics>=5.3.0
Requires-Dist: itk>=5.3.0
Requires-Dist: onnxruntime>=1.16.2
Requires-Dist: pandas>=1.4.0
Requires-Dist: pyarrow>=6.0.0
Requires-Dist: pydicom>=2.2.0
Requires-Dist: python-gdcm>=3.0.10
Requires-Dist: tabulate>=0.9.0
